<?xml version="1.0" encoding="UTF-8"?><saml2p:AuthnRequest xmlns:saml2p="urn:oasis:names:tc:SAML:2.0:protocol" xmlns:ds="http://www.w3.org/2000/09/xmldsig#" xmlns:eidas="http://eidas.europa.eu/saml-extensions" xmlns:saml2="urn:oasis:names:tc:SAML:2.0:assertion" xmlns:eidas-natural="http://eidas.europa.eu/attributes/naturalperson" Destination="https://se-pasarela.clave.gob.es/Proxy2/ServiceProvider" ProviderName="21114293V_E04975701" ID="_0fcef07e-d521-445e-a896-a7b0dc52e35d" IssueInstant="2025-07-17T20:28:26" AssertionConsumerServiceURL="http://localhost:3000/acs" Consent="urn:oasis:names:tc:SAML:2.0:consent:unspecified" ForceAuthn="true" IsPassive="false" Version="2.0"><saml2p:Extensions><eidas:SPType>public</eidas:SPType><eidas:RequestedAttributes/></saml2p:Extensions><saml2p:NameIDPolicy AllowCreate="true" Format="urn:oasis:names:tc:SAML:1.1:nameid-format:unspecified"/><saml2p:RequestedAuthnContext Comparison="minimum"><saml2:AuthnContextClassRef>http://eidas.europa.eu/LoA/low</saml2:AuthnContextClassRef></saml2p:RequestedAuthnContext></saml2p:AuthnRequest>